mypackage123456/__init__.py
mypackage123456/hello.py
mypackage123456-2.1.200.dist-info/METADATA
mypackage123456-2.1.200.dist-info/WHEEL
mypackage123456-2.1.200.dist-info/top_level.txt
mypackage123456-2.1.200.dist-info/RECORD
