Metadata-Version: 2.1
Name: mypackage123456
Version: 2.1.200
Summary: Test publishing package
Author: Khai Truong
Author-email: <khaitruong209@gmail.com>
License: UNKNOWN
Platform: UNKNOWN
Requires-Dist: flask
